setup.cfg
setup.py
Provider/IServiceHandler.py
Provider/Service.py
Provider/__init__.py
Services/__init__.py
Services/ContextService/Context.py
Services/ContextService/ContextExceptions.py
Services/ContextService/ContextInfo.py
Services/ContextService/ContextMonitor.py
Services/ContextService/ContextProvider.py
Services/ContextService/__init__.py
Services/Monitor/Monitor.py
Services/Monitor/ServiceMonitor.py
Services/Monitor/__init__.py
Tools/__init__.py
Tools/conf_command.py
Tools/create_service.py
Tools/display.py
Tools/service_context.py
Utils/ModuleLoader.py
Utils/MongoHandler.py
Utils/PacketHandler.py
Utils/Utilities.py
Utils/XMLParser.py
Utils/__init__.py
zmicroservices.egg-info/PKG-INFO
zmicroservices.egg-info/SOURCES.txt
zmicroservices.egg-info/dependency_links.txt
zmicroservices.egg-info/top_level.txt