Metadata-Version: 1.1
Name: zmicroservices
Version: 1.0.0
Summary: An alternative way for doing micro-services.
Home-page: https://github.com/renatosamperio/context_task_queue
Author: Renato Samperio
Author-email: renatosamperio@gmail.com
License: GPL 3.0
Download-URL: https://github.com/renatosamperio/context_task_queue/tarball/1.0
Keywords: microservices,zmq,distributed apps
Platform: Ubuntu 16.04
Classifier: Development Status :: 3 - Alpha
Classifier: Topic :: Utilities
Classifier: Topic :: Software Development :: Libraries
Classifier: Topic :: System :: Monitoring
Classifier: Topic :: System :: Software Distribution
Classifier: License :: OSI Approved :: GNU General Public License v3 (GPLv3)
Classifier: Natural Language :: English
Classifier: Operating System :: POSIX :: Linux
Classifier: Programming Language :: Python :: 2.7
